rsma/__init__.py
rsma/_device.py
rsma/_logger.py
rsma-0.1.1.dist-info/METADATA
rsma-0.1.1.dist-info/WHEEL
rsma-0.1.1.dist-info/licenses/LICENSE
rsma-0.1.1.dist-info/RECORD
