Metadata-Version: 2.4
Name: rsma
Version: 0.1.1
Summary: Robotic State Management Architecture for Robotics Applications in Python
License: MIT License
License-File: LICENSE
Requires-Python: >=3.12
Requires-Dist: twine>=6.0.1
